netbox_qrcode/__init__.py
netbox_qrcode/template_content.py
netbox_qrcode/template_content_functions.py
netbox_qrcode/utilities.py
netbox_qrcode/version.py
netbox_qrcode/templates/netbox_qrcode/qrcode.html
netbox_qrcode/templates/netbox_qrcode/qrcode3.html
netbox_qrcode/templates/netbox_qrcode/qrcode3_sub_qrcode.html
netbox_qrcode-0.0.20.dist-info/licenses/LICENSE
netbox_qrcode-0.0.20.dist-info/METADATA
netbox_qrcode-0.0.20.dist-info/WHEEL
netbox_qrcode-0.0.20.dist-info/top_level.txt
netbox_qrcode-0.0.20.dist-info/RECORD
