Metadata-Version: 2.4
Name: netbox-qrcode
Version: 0.0.20
Summary: QR Code generation for netbox objects
Home-page: https://github.com/netbox-community/netbox-qrcode
Author: Nikolay Yuzefovich
Author-email: mgk.kolek@gmail.com
Classifier: Development Status :: 2 - Pre-Alpha
Classifier: License :: OSI Approved :: Apache Software License
Classifier: Framework :: Django
Classifier: Programming Language :: Python :: 3
License-File: LICENSE
Requires-Dist: qrcode
Requires-Dist: Pillow
Dynamic: author
Dynamic: author-email
Dynamic: classifier
Dynamic: description
Dynamic: description-content-type
Dynamic: home-page
Dynamic: license-file
Dynamic: requires-dist
Dynamic: summary
